okex3/__init__.py
okex3/client.py
okex3/consts.py
okex3/exceptions.py
okex3/utils.py
okex3/websocket.py
okex3/api/__init__.py
okex3/api/account.py
okex3/api/ett.py
okex3/api/future.py
okex3/api/lever.py
okex3/api/spot.py
okex3-0.1.1.dist-info/METADATA
okex3-0.1.1.dist-info/WHEEL
okex3-0.1.1.dist-info/top_level.txt
okex3-0.1.1.dist-info/RECORD
